fixml/__init__.py
fixml/cli/__init__.py
fixml/cli/checklist.py
fixml/cli/export.py
fixml/cli/main.py
fixml/cli/repository.py
fixml/cli/utils.py
fixml/consistency_check.py
fixml/data/__init__.py
fixml/data/checklist/checklist.csv/overview.csv
fixml/data/checklist/checklist.csv/tests.csv
fixml/data/checklist/checklist.csv/topics.csv
fixml/data/checklist/references.bib
fixml/data/templates/checklist.md.jinja
fixml/data/templates/eval_report.md.jinja
fixml/modules/__init__.py
fixml/modules/checklist/__init__.py
fixml/modules/checklist/checklist.py
fixml/modules/code_analyzer/__init__.py
fixml/modules/code_analyzer/analyzers/__init__.py
fixml/modules/code_analyzer/analyzers/python.py
fixml/modules/code_analyzer/example.py
fixml/modules/code_analyzer/git.py
fixml/modules/code_analyzer/repo.py
fixml/modules/llm_eval/__init__.py
fixml/modules/llm_eval/consistency_eval.py
fixml/modules/mixins.py
fixml/modules/template.py
fixml/modules/utils.py
fixml/modules/workflow/__init__.py
fixml/modules/workflow/parse.py
fixml/modules/workflow/prompt_format.py
fixml/modules/workflow/response.py
fixml/modules/workflow/runners/__init__.py
fixml/modules/workflow/runners/base.py
fixml/modules/workflow/runners/evaluator.py
fixml/modules/workflow/runners/generator.py
fixml-0.1.1.dist-info/LICENSE
fixml-0.1.1.dist-info/METADATA
fixml-0.1.1.dist-info/WHEEL
fixml-0.1.1.dist-info/entry_points.txt
fixml-0.1.1.dist-info/RECORD
