Metadata-Version: 2.1
Name: fixml
Version: 0.1.1
Summary: Package for automated test evaluation and creation
License: MIT
Author: John Shiu, Orix Au Yeung, Tony Shum, Yingzi Jin
Requires-Python: >=3.12,<4.0
Classifier: License :: OSI Approved :: MIT License
Classifier: Programming Language :: Python :: 3
Classifier: Programming Language :: Python :: 3.12
Requires-Dist: chardet (>=5.2.0,<6.0.0)
Requires-Dist: fire (>=0.6.0,<0.7.0)
Requires-Dist: gitpython (>=3.1.43,<4.0.0)
Requires-Dist: jinja2 (>=3.1.4,<4.0.0)
Requires-Dist: langchain (>=0.2.1,<0.3.0)
Requires-Dist: langchain-community (>=0.2.1,<0.3.0)
Requires-Dist: langchain-core (>=0.2.1,<0.3.0)
Requires-Dist: langchain-openai (>=0.1.7,<0.2.0)
Requires-Dist: pandas[output-formatting] (>=2.2.2,<3.0.0)
Requires-Dist: pydantic (>=2.7.4,<3.0.0)
Requires-Dist: pypandoc (>=1.13,<2.0)
Requires-Dist: python-dotenv (>=1.0.1,<2.0.0)
Requires-Dist: ruamel-yaml (>=0.18.6,<0.19.0)
Requires-Dist: tqdm (>=4.66.4,<5.0.0)
